msitrees/__init__.py
msitrees/_base.py
msitrees/_core.cp38-win_amd64.pyd
msitrees/_node.py
msitrees/ensemble.py
msitrees/tree.py
msitrees-0.2.dist-info/LICENSE
msitrees-0.2.dist-info/METADATA
msitrees-0.2.dist-info/WHEEL
msitrees-0.2.dist-info/top_level.txt
msitrees-0.2.dist-info/RECORD
