Metadata-Version: 2.1
Name: msitrees
Version: 0.2
Summary: MSI based machine learning algorithms
Home-page: https://github.com/xadrianzetx/msitrees
Author: xadrianzetx
License: UNKNOWN
Project-URL: Source Code, https://github.com/xadrianzetx/msitrees/tree/master
Project-URL: Documentation, https://msitrees.readthedocs.io/en/latest/index.html
Platform: UNKNOWN
Classifier: Development Status :: 5 - Production/Stable
Classifier: Intended Audience :: Developers
Classifier: Intended Audience :: Science/Research
Classifier: License :: OSI Approved :: MIT License
Classifier: Operating System :: Microsoft :: Windows
Classifier: Operating System :: POSIX :: Linux
Classifier: Programming Language :: C++
Classifier: Programming Language :: Python :: 3
Classifier: Topic :: Scientific/Engineering :: Artificial Intelligence
Classifier: Topic :: Scientific/Engineering :: Mathematics
Classifier: Topic :: Software Development :: Libraries
Requires-Python: >=3.5
Requires-Dist: numpy (>=1.18)
Requires-Dist: pandas (>=1.0.0)
Requires-Dist: joblib (>=0.14.0)
